openstef_dbc/__init__.py
openstef_dbc/__main__.py
openstef_dbc/data_interface.py
openstef_dbc/database.py
openstef_dbc/ktp_api.py
openstef_dbc/settings.py
openstef_dbc/utils.py
openstef_dbc/log/__init__.py
openstef_dbc/log/logging.py
openstef_dbc/log/processors.py
openstef_dbc/models/__init__.py
openstef_dbc/models/measurement.py
openstef_dbc/models/switch_state.py
openstef_dbc/services/__init__.py
openstef_dbc/services/ems.py
openstef_dbc/services/model_input.py
openstef_dbc/services/prediction_job.py
openstef_dbc/services/predictions.py
openstef_dbc/services/predictor.py
openstef_dbc/services/splitting.py
openstef_dbc/services/systems.py
openstef_dbc/services/weather.py
openstef_dbc/services/write.py
openstef_dbc-3.8.11.dist-info/licenses/LICENSE
openstef_dbc-3.8.11.dist-info/METADATA
openstef_dbc-3.8.11.dist-info/WHEEL
openstef_dbc-3.8.11.dist-info/top_level.txt
openstef_dbc-3.8.11.dist-info/RECORD
