Metadata-Version: 2.4
Name: openstef_dbc
Version: 3.8.11
Summary: Database Connection for OpenSTEF
Home-page: https://github.com/openstef/openstef-dbc
Author: Alliander N.V
Author-email: korte.termijn.prognoses@alliander.com
License: MPL-2.0
Keywords: database,energy,forecasting,machinelearning
Classifier: Development Status :: 5 - Production/Stable
Classifier: Intended Audience :: Developers
Classifier: License :: OSI Approved :: Mozilla Public License 2.0 (MPL 2.0)
Classifier: Programming Language :: Python :: 3.12
Classifier: Programming Language :: Python :: 3.13
Requires-Python: >=3.12.0
License-File: LICENSE
Requires-Dist: ciso8601~=2.3.0
Requires-Dist: geopy~=2.3.0
Requires-Dist: openstef~=3.4.87
Requires-Dist: mlflow-skinny<4.0.0,>=3.5.1
Requires-Dist: pydantic-settings<3.0.0,>=2.1.0
Requires-Dist: influxdb-client~=1.36.1
Requires-Dist: mysql-connector-python>=9.1.0
Requires-Dist: psycopg2-binary~=2.9.6
Requires-Dist: PyMySQL<2.0.0,>=1.0.2
Requires-Dist: PyYAML<7.0.0,>=6.0
Requires-Dist: requests<3.0.0,>=2.28.1
Requires-Dist: SQLAlchemy
Dynamic: author
Dynamic: author-email
Dynamic: classifier
Dynamic: description
Dynamic: description-content-type
Dynamic: home-page
Dynamic: keywords
Dynamic: license
Dynamic: license-file
Dynamic: requires-dist
Dynamic: requires-python
Dynamic: summary
